{
  "type": "FeatureCollection",
  "features": [
    {
      "type": "Feature",
      "geometry": {
        "type": "Point",
        "coordinates": [
          103.311486,
          15.519307
        ]
      },
      "properties": {
        "name": "Initial Transformer",
        "group": "initial"
      }
    },
    {
      "type": "Feature",
      "geometry": {
        "type": "Point",
        "coordinates": [
          103.311656,
          15.518572
        ]
      },
      "properties": {
        "name": "Splitting Point",
        "group": "splitting"
      }
    },
    {
      "type": "Feature",
      "geometry": {
        "type": "Point",
        "coordinates": [
          103.311684,
          15.518202
        ]
      },
      "properties": {
        "name": "Group 1 Transformer",
        "group": "group1"
      }
    },
    {
      "type": "Feature",
      "geometry": {
        "type": "Point",
        "coordinates": [
          103.311437,
          15.519813
        ]
      },
      "properties": {
        "name": "Group 2 Transformer",
        "group": "group2"
      }
    }
  ]
}